framework/__init__.py
framework/config.py
framework/driver_factory.py
framework/logger.py
framework/order.py
framework/pdf_report.py
framework/pytest_plugin.py
framework/reporting.py
operations/__init__.py
operations/web.py
pybrowsertestfw-0.1.0.dist-info/licenses/LICENSE
video/__init__.py
video/pyscreenrec.py
video/recorder.py
pybrowsertestfw-0.1.0.dist-info/METADATA
pybrowsertestfw-0.1.0.dist-info/WHEEL
pybrowsertestfw-0.1.0.dist-info/entry_points.txt
pybrowsertestfw-0.1.0.dist-info/top_level.txt
pybrowsertestfw-0.1.0.dist-info/RECORD
