Metadata-Version: 2.4
Name: pybrowsertestfw
Version: 0.1.0
Summary: Pytest browser test framework
License:                                  Apache License
Requires-Python: <3.14,>=3.9
License-File: LICENSE
Requires-Dist: pytest>=8.4.2
Requires-Dist: selenium>=4.37.0
Requires-Dist: appium-python-client>=5.2.4
Requires-Dist: PyYAML==6.0.3
Requires-Dist: pytest-html==4.1.1
Requires-Dist: pytest-json-report==1.5.0
Requires-Dist: reportlab==4.4.6
Requires-Dist: screeninfo==0.8.1
Requires-Dist: numpy==2.2.0
Requires-Dist: opencv-python==4.12.0.88
Requires-Dist: mss==10.1.0
Dynamic: license-file
